Workbook
Name FullDataset: Raw_Data!$A$1:$AQ$1471
Name AttritionColumn: Raw_Data!$B$2:$B$1471
Name IncomeColumn: Raw_Data!$R$2:$R$1471

Sheet Cover_Navigation
A1: Employee Burnout & Attrition Intelligence
A5: Analytical Workbook - Comprehensive HR Analytics & Predictive Insights
A6: Generated: August 15, 2026
A7: Dataset: 1,470 Employees | 43 Features | 16.1% Attrition Rate
B9: WORKBOOK NAVIGATION
B11: # | C11: Sheet Name | D11: Description
B12: 1 | C12: Data_Dictionary | D12: Column definitions, data types, and valid ranges for all 43 features
B13: 2 | C13: Raw_Data | D13: Complete dataset (1,470 rows) formatted as an Excel Table
B14: 3 | C14: KPI_Dashboard | D14: Key performance indicators with formula-driven metrics
B15: 4 | C15: Pivot_Summary | D15: Pre-computed pivot tables: Attrition by Department, Salary, OverTime
B16: 5 | C16: What_If_Model | D16: Scenario analysis: Model attrition reduction from policy changes
B17: 6 | C17: KPI_Validation | D17: Cross-validation of Python computations vs Excel formulas
B20: Project: Employee Burnout & Attrition Intelligence | Portfolio Analytics

Sheet Data_Dictionary
A1: Data Dictionary
A2: Complete reference for all 43 columns in the employee attrition dataset
A4: Column Name | B4: Data Type | C4: Category | D4: Description | E4: Valid Range
A5: Age | B5: Integer | C5: Real | D5: Age of the employee | E5: 18-60
A6: Attrition | B6: Categorical | C6: Real | D6: Whether the employee left the company | E6: Yes/No
A7: BusinessTravel | B7: Categorical | C7: Real | D7: Frequency of business travel | E7: Non-Travel/Travel_Rarely/Travel_Frequently
A8: DailyRate | B8: Integer | C8: Real | D8: Daily rate of pay | E8: 102-1499
A9: Department | B9: Categorical | C9: Real | D9: Department of the employee | E9: Sales/Research & Development/Human Resources
A10: DistanceFromHome | B10: Integer | C10: Real | D10: Distance from home to workplace in miles | E10: 1-29
A11: Education | B11: Integer | C11: Real | D11: Education level (1=Below College to 5=Doctor) | E11: 1-5
A12: EducationField | B12: Categorical | C12: Real | D12: Field of education | E12: Life Sciences/Medical/Marketing/Technical Degree/Human Resources/Other
A13: EmployeeID | B13: Integer | C13: Real | D13: Unique employee identifier | E13: 1-1470
A14: EnvironmentSatisfaction | B14: Integer | C14: Real | D14: Satisfaction with work environment (1=Low to 4=Very High) | E14: 1-4
A15: Gender | B15: Categorical | C15: Real | D15: Gender of the employee | E15: Male/Female
... A47: TenureBand | B47: Categorical | C47: Engineered | D47: Tenure band based on YearsAtCompany | E47: New (0-1)/Settling (2-3)/Established (4-5)/Veteran (6-10)/Lifer (10+)

Sheet Raw_Data
A1: Age | B1: Attrition | C1: BusinessTravel | D1: DailyRate | E1: Department | F1: DistanceFromHome | G1: Education | H1: EducationField | I1: EmployeeID | J1: EnvironmentSatisfaction | K1: Gender | L1: HourlyRate | M1: JobInvolvement | N1: JobLevel | O1: JobRole | P1: JobSatisfaction | Q1: MaritalStatus | R1: MonthlyIncome | S1: MonthlyRate | T1: NumCompaniesWorked | U1: OverTime | V1: PercentSalaryHike | W1: PerformanceRating | X1: RelationshipSatisfaction | Y1: StockOptionLevel | Z1: TotalWorkingYears | AA1: TrainingTimesLastYear | AB1: WorkLifeBalance | AC1: YearsAtCompany | AD1: YearsInCurrentRole | AE1: YearsSinceLastPromotion | AF1: YearsWithCurrManager | AG1: WorkloadScore | AH1: WeeklyHoursWorked | AI1: MonthlyMeetings | AJ1: CompensationSatisfaction | AK1: CareerGrowthPerception | AL1: ManagerSupportScore | AM1: WorkModel | AN1: ProductivityScore | AO1: SalaryBand | AP1: ExperienceBand | AQ1: TenureBand
A2: 41 | B2: Yes | C2: Travel_Rarely | D2: 1102 | E2: Sales | F2: 1 | G2: 2 | H2: Life Sciences | I2: 1 | J2: 2 | K2: Female | L2: 94 | M2: 3 | N2: 2 | O2: Sales Executive | P2: 4 | Q2: Single | R2: 5993 | S2: 19479 | T2: 8 | U2: Yes | V2: 11 | W2: 3 | X2: 1 | Y2: 0 | Z2: 8 | AA2: 0 | AB2: 1 | AC2: 6 | AD2: 4 | AE2: 0 | AF2: 5 | AG2: 5 | AH2: 55.9 | AI2: 9 | AJ2: 3 | AK2: 1 | AL2: 4 | AM2: Remote | AN2: 5 | AO2: Below Average | AP2: Mid (6-10) | AQ2: Veteran (6-10)
A3: 49 | B3: No | C3: Travel_Frequently | D3: 279 | E3: Research & Development | F3: 8 | G3: 1 | H3: Life Sciences | I3: 2 | J3: 3 | K3: Male | L3: 61 | M3: 2 | N3: 2 | O3: Research Scientist | P3: 2 | Q3: Married | R3: 5130 | S3: 24907 | T3: 1 | U3: No | V3: 23 | W3: 4 | X3: 4 | Y3: 1 | Z3: 10 | AA3: 3 | AB3: 3 | AC3: 10 | AD3: 7 | AE3: 1 | AF3: 7 | AG3: 3 | AH3: 38.7 | AI3: 8 | AJ3: 5 | AK3: 4 | AL3: 4 | AM3: Onsite | AN3: 4 | AO3: Below Average | AP3: Mid (6-10) | AQ3: Veteran (6-10)
A4: 37 | B4: Yes | C4: Travel_Rarely | D4: 1373 | E4: Research & Development | F4: 2 | G4: 2 | H4: Other | I4: 4 | J4: 4 | K4: Male | L4: 92 | M4: 2 | N4: 1 | O4: Laboratory Technician | P4: 3 | Q4: Single | R4: 2090 | S4: 2396 | T4: 6 | U4: Yes | V4: 15 | W4: 3 | X4: 2 | Y4: 0 | Z4: 7 | AA4: 3 | AB4: 3 | AC4: 0 | AD4: 0 | AE4: 0 | AF4: 0 | AG4: 5 | AH4: 53.4 | AI4: 9 | AJ4: 1 | AK4: 3 | AL4: 3 | AM4: Remote | AN4: 2 | AO4: Low | AP4: Mid (6-10) | AQ4: New (0-1)
A5: 33 | B5: No | C5: Travel_Frequently | D5: 1392 | E5: Research & Development | F5: 3 | G5: 4 | H5: Life Sciences | I5: 5 | J5: 4 | K5: Female | L5: 56 | M5: 3 | N5: 1 | O5: Research Scientist | P5: 3 | Q5: Married | R5: 2909 | S5: 23159 | T5: 1 | U5: Yes | V5: 11 | W5: 3 | X5: 3 | Y5: 0 | Z5: 8 | AA5: 3 | AB5: 3 | AC5: 8 | AD5: 7 | AE5: 3 | AF5: 0 | AG5: 5 | AH5: 46.5 | AI5: 10 | AJ5: 3 | AK5: 2 | AL5: 4 | AM5: Onsite | AN5: 3 | AO5: Low | AP5: Mid (6-10) | AQ5: Veteran (6-10)
A6: 27 | B6: No | C6: Travel_Rarely | D6: 591 | E6: Research & Development | F6: 2 | G6: 1 | H6: Medical | I6: 7 | J6: 1 | K6: Male | L6: 40 | M6: 3 | N6: 1 | O6: Laboratory Technician | P6: 2 | Q6: Married | R6: 3468 | S6: 16632 | T6: 9 | U6: No | V6: 12 | W6: 3 | X6: 4 | Y6: 1 | Z6: 6 | AA6: 3 | AB6: 3 | AC6: 2 | AD6: 2 | AE6: 2 | AF6: 2 | AG6: 3 | AH6: 36.5 | AI6: 5 | AJ6: 4 | AK6: 3 | AL6: 2 | AM6: Onsite | AN6: 3 | AO6: Below Average | AP6: Mid (6-10) | AQ6: Settling (2-3)
A7: 32 | B7: No | C7: Travel_Frequently | D7: 1005 | E7: Research & Development | F7: 2 | G7: 2 | H7: Life Sciences | I7: 8 | J7: 4 | K7: Male | L7: 79 | M7: 3 | N7: 1 | O7: Laboratory Technician | P7: 4 | Q7: Single | R7: 3068 | S7: 11864 | T7: 0 | U7: No | V7: 13 | W7: 3 | X7: 3 | Y7: 0 | Z7: 8 | AA7: 2 | AB7: 2 | AC7: 7 | AD7: 7 | AE7: 3 | AF7: 6 | AG7: 3 | AH7: 43 | AI7: 7 | AJ7: 3 | AK7: 3 | AL7: 5 | AM7: Hybrid | AN7: 2 | AO7: Below Average | AP7: Mid (6-10) | AQ7: Veteran (6-10)
A8: 59 | B8: No | C8: Travel_Rarely | D8: 1324 | E8: Research & Development | F8: 3 | G8: 3 | H8: Medical | I8: 10 | J8: 3 | K8: Female | L8: 81 | M8: 4 | N8: 1 | O8: Laboratory Technician | P8: 1 | Q8: Married | R8: 2670 | S8: 9964 | T8: 4 | U8: Yes | V8: 20 | W8: 4 | X8: 1 | Y8: 3 | Z8: 12 | AA8: 3 | AB8: 2 | AC8: 1 | AD8: 0 | AE8: 0 | AF8: 0 | AG8: 5 | AH8: 45.5 | AI8: 5 | AJ8: 4 | AK8: 4 | AL8: 2 | AM8: Onsite | AN8: 4 | AO8: Low | AP8: Senior (11-20) | AQ8: New (0-1)
A9: 30 | B9: No | C9: Travel_Rarely | D9: 1358 | E9: Research & Development | F9: 24 | G9: 1 | H9: Life Sciences | I9: 11 | J9: 4 | K9: Male | L9: 67 | M9: 3 | N9: 1 | O9: Laboratory Technician | P9: 3 | Q9: Divorced | R9: 2693 | S9: 13335 | T9: 1 | U9: No | V9: 22 | W9: 4 | X9: 2 | Y9: 1 | Z9: 1 | AA9: 2 | AB9: 3 | AC9: 1 | AD9: 0 | AE9: 0 | AF9: 0 | AG9: 4 | AH9: 41.3 | AI9: 11 | AJ9: 3 | AK9: 3 | AL9: 5 | AM9: Remote | AN9: 4 | AO9: Low | AP9: Entry (0-2) | AQ9: New (0-1)
A10: 38 | B10: No | C10: Travel_Frequently | D10: 216 | E10: Research & Development | F10: 23 | G10: 3 | H10: Life Sciences | I10: 12 | J10: 4 | K10: Male | L10: 44 | M10: 2 | N10: 3 | O10: Manufacturing Director | P10: 3 | Q10: Single | R10: 9526 | S10: 8787 | T10: 0 | U10: No | V10: 21 | W10: 4 | X10: 2 | Y10: 0 | Z10: 10 | AA10: 2 | AB10: 3 | AC10: 9 | AD10: 7 | AE10: 1 | AF10: 8 | AG10: 3 | AH10: 39.1 | AI10: 14 | AJ10: 4 | AK10: 4 | AL10: 4 | AM10: Hybrid | AN10: 3 | AO10: Average | AP10: Mid (6-10) | AQ10: Veteran (6-10)
A11: 36 | B11: No | C11: Travel_Rarely | D11: 1299 | E11: Research & Development | F11: 27 | G11: 3 | H11: Medical | I11: 13 | J11: 3 | K11: Male | L11: 94 | M11: 3 | N11: 2 | O11: Healthcare Representative | P11: 3 | Q11: Married | R11: 5237 | S11: 16577 | T11: 6 | U11: No | V11: 13 | W11: 3 | X11: 2 | Y11: 2 | Z11: 17 | AA11: 3 | AB11: 2 | AC11: 7 | AD11: 7 | AE11: 7 | AF11: 7 | AG11: 4 | AH11: 40.2 | AI11: 11 | AJ11: 4 | AK11: 4 | AL11: 4 | AM11: Onsite | AN11: 3 | AO11: Below Average | AP11: Senior (11-20) | AQ11: Veteran (6-10)
A12: 35 | B12: No | C12: Travel_Rarely | D12: 809 | E12: Research & Development | F12: 16 | G12: 3 | H12: Medical | I12: 14 | J12: 1 | K12: Male | L12: 84 | M12: 4 | N12: 1 | O12: Laboratory Technician | P12: 2 | Q12: Married | R12: 2426 | S12: 16479 | T12: 0 | U12: No | V12: 13 | W12: 3 | X12: 3 | Y12: 1 | Z12: 6 | AA12: 5 | AB12: 3 | AC12: 5 | AD12: 4 | AE12: 0 | AF12: 3 | AG12: 3 | AH12: 42.5 | AI12: 9 | AJ12: 3 | AK12: 4 | AL12: 2 | AM12: Hybrid | AN12: 5 | AO12: Low | AP12: Mid (6-10) | AQ12: Established (4-5)
A13: 29 | B13: No | C13: Travel_Rarely | D13: 153 | E13: Research & Development | F13: 15 | G13: 2 | H13: Life Sciences | I13: 15 | J13: 4 | K13: Female | L13: 49 | M13: 2 | N13: 2 | O13: Laboratory Technician | P13: 3 | Q13: Single | R13: 4193 | S13: 12682 | T13: 0 | U13: Yes | V13: 12 | W13: 3 | X13: 4 | Y13: 0 | Z13: 10 | AA13: 3 | AB13: 3 | AC13: 9 | AD13: 5 | AE13: 0 | AF13: 8 | AG13: 4 | AH13: 54.3 | AI13: 11 | AJ13: 4 | AK13: 4 | AL13: 4 | AM13: Remote | AN13: 2 | AO13: Below Average | AP13: Mid (6-10) | AQ13: Veteran (6-10)
... A1471: 34 | B1471: No | C1471: Travel_Rarely | D1471: 628 | E1471: Research & Development | F1471: 8 | G1471: 3 | H1471: Medical | I1471: 2068 | J1471: 2 | K1471: Male | L1471: 82 | M1471: 4 | N1471: 2 | O1471: Laboratory Technician | P1471: 3 | Q1471: Married | R1471: 4404 | S1471: 10228 | T1471: 2 | U1471: No | V1471: 12 | W1471: 3 | X1471: 1 | Y1471: 0 | Z1471: 6 | AA1471: 3 | AB1471: 4 | AC1471: 4 | AD1471: 3 | AE1471: 1 | AF1471: 2 | AG1471: 4 | AH1471: 38.7 | AI1471: 11 | AJ1471: 4 | AK1471: 4 | AL1471: 3 | AM1471: Onsite | AN1471: 4 | AO1471: Below Average | AP1471: Mid (6-10) | AQ1471: Established (4-5)

Sheet KPI_Dashboard
B2: KEY PERFORMANCE INDICATORS
B3: Formula-driven metrics referencing the Raw_Data sheet
B5: Total Employees | E5: Attrition Rate | H5: Avg Monthly Income | K5: Avg Job Satisfaction
B6: =COUNTA(Raw_Data!B2:B1471) | E6: =COUNTIF(Raw_Data!B2:B1471,"Yes")/COUNTA(Raw_Data!B2:B1471) | H6: =AVERAGE(Raw_Data!R2:R1471) | K6: =AVERAGE(Raw_Data!P2:P1471)
B11: Avg WorkLife Balance | E11: Avg Workload Score | H11: Overtime Rate | K11: Avg Manager Support
B12: =AVERAGE(Raw_Data!AB2:AB1471) | E12: =AVERAGE(Raw_Data!AG2:AG1471) | H12: =COUNTIF(Raw_Data!U2:U1471,"Yes")/COUNTA(Raw_Data!U2:U1471) | K12: =AVERAGE(Raw_Data!AL2:AL1471)

Sheet Pivot_Summary
A1: Attrition by Department
A2: Department | B2: Total Employees | C2: Attrited | D2: Attrition Rate
A3: Human Resources | B3: 63 | C3: 12 | D3: 0.19047619
A4: Research & Development | B4: 961 | C4: 133 | D4: 0.1383975
A5: Sales | B5: 446 | C5: 92 | D5: 0.20627803
A8: Attrition by Salary Band
A9: Salary Band | B9: Total Employees | C9: Attrited | D9: Attrition Rate
A10: Low | B10: 395 | C10: 113 | D10: 0.28607595
A11: Below Average | B11: 519 | C11: 66 | D11: 0.12716763
A12: Average | B12: 275 | C12: 33 | D12: 0.12
A13: Above Average | B13: 148 | C13: 20 | D13: 0.13513514
A14: High | B14: 133 | C14: 5 | D14: 0.037593985
A17: Attrition by OverTime Status
A18: OverTime | B18: Total Employees | C18: Attrited | D18: Attrition Rate
A19: No | B19: 1054 | C19: 110 | D19: 0.10436433
A20: Yes | B20: 416 | C20: 127 | D20: 0.30528846
A23: Average Satisfaction Metrics by Department
A24: Department | B24: Job Satisfaction | C24: Environment Satisfaction | D24: WorkLife Balance | E24: Manager Support
A25: Human Resources | B25: 2.6 | C25: 2.68 | D25: 2.92 | E25: 3.63
A26: Research & Development | B26: 2.73 | C26: 2.74 | D26: 2.73 | E26: 3.48
A27: Sales | B27: 2.75 | C27: 2.68 | D27: 2.82 | E27: 3.47

Sheet What_If_Model
B2: WHAT-IF SCENARIO ANALYSIS
B3: Model the impact of HR policy changes on projected attrition
B5: MODEL ASSUMPTIONS (Based on Observed Data)
B6: Current Overall Attrition Rate: 16.1%
B7: Low Salary Band Attrition: 28.6% vs High Salary Band: 3.8%
B8: Observed Salary Effect (Low-High gap): 24.8% attrition difference
B9: Long Promotion Gap (5+ yrs) Attrition: 14.2% vs Recent Promotion (0-1 yr): 17.0%
B10: Observed Promotion Effect: -2.7% attrition difference
B11: Model assumes linear interpolation of these observed effects for intermediate changes.
B14: SCENARIO INPUTS
B15: Salary Increase %: | D15: 0.1
B16: Promotion Gap Reduction %: | D16: 0.2
B17: (Edit the yellow cells above to run different scenarios)
B19: PROJECTED OUTCOMES
B20: Current Attrition Rate: | D20: 0.16122449
B21: Current Attrition Count: | D21: 237
B23: Attrition Reduction from Salary: | D23: =0.2485*D15
B24: Attrition Reduction from Promotions: | D24: =-0.0272*D16
B26: Total Projected Attrition Reduction: | D26: =D23+D24
B27: New Projected Attrition Rate: | D27: =MAX(D20-D26,0)
B28: Additional Employees Retained: | D28: =ROUND(D26*1470,0)
B30: Note: This is a simplified linear model based on observed correlations in the dataset. Actual outcomes depend on many additional factors not captured here.

Sheet KPI_Validation
A1: KPI Validation: Python vs Excel
A2: Side-by-side comparison ensuring computational accuracy
A4: KPI Name | B4: Python Value | C4: Excel Value | D4: Match | E4: Tolerance
A5: Total Employees | B5: 1470 | C5: =COUNTA(Raw_Data!B2:B1471) | D5: =IF(ABS(B5-C5)<=0.001,"TRUE","FALSE") | E5: 0.001
A6: Attrition Rate | B6: 0.1612 | C6: =COUNTIF(Raw_Data!B2:B1471,"Yes")/COUNTA(Raw_Data!B2:B1471) | D6: =IF(ABS(B6-C6)<=0.001,"TRUE","FALSE") | E6: 0.001
A7: Avg Monthly Income | B7: 6502.93 | C7: =AVERAGE(Raw_Data!R2:R1471) | D7: =IF(ABS(B7-C7)<=0.01,"TRUE","FALSE") | E7: 0.01
A8: Avg Job Satisfaction | B8: 2.7286 | C8: =AVERAGE(Raw_Data!P2:P1471) | D8: =IF(ABS(B8-C8)<=0.001,"TRUE","FALSE") | E8: 0.001
A9: Avg WorkLife Balance | B9: 2.7612 | C9: =AVERAGE(Raw_Data!AB2:AB1471) | D9: =IF(ABS(B9-C9)<=0.001,"TRUE","FALSE") | E9: 0.001
A10: Avg Workload Score | B10: 3.4565 | C10: =AVERAGE(Raw_Data!AG2:AG1471) | D10: =IF(ABS(B10-C10)<=0.001,"TRUE","FALSE") | E10: 0.001
A11: Overtime Rate | B11: 0.283 | C11: =COUNTIF(Raw_Data!U2:U1471,"Yes")/COUNTA(Raw_Data!U2:U1471) | D11: =IF(ABS(B11-C11)<=0.001,"TRUE","FALSE") | E11: 0.001
A12: Avg Manager Support | B12: 3.4864 | C12: =AVERAGE(Raw_Data!AL2:AL1471) | D12: =IF(ABS(B12-C12)<=0.001,"TRUE","FALSE") | E12: 0.001
A13: Avg Age | B13: 36.9238 | C13: =AVERAGE(Raw_Data!A2:A1471) | D13: =IF(ABS(B13-C13)<=0.001,"TRUE","FALSE") | E13: 0.001
A15: Validation Summary: | B15: =COUNTIF(D5:D13,"TRUE")&" of 9 KPIs match"
